blebox_uniapi/__init__.py
blebox_uniapi/binary_sensor.py
blebox_uniapi/box.py
blebox_uniapi/box_types.py
blebox_uniapi/button.py
blebox_uniapi/climate.py
blebox_uniapi/cover.py
blebox_uniapi/error.py
blebox_uniapi/feature.py
blebox_uniapi/jfollow.py
blebox_uniapi/light.py
blebox_uniapi/sensor.py
blebox_uniapi/session.py
blebox_uniapi/switch.py
blebox_uniapi-2.5.0.dist-info/LICENSE
blebox_uniapi-2.5.0.dist-info/METADATA
blebox_uniapi-2.5.0.dist-info/WHEEL
blebox_uniapi-2.5.0.dist-info/top_level.txt
blebox_uniapi-2.5.0.dist-info/RECORD
