Metadata-Version: 2.1
Name: blebox_uniapi
Version: 2.5.0
Summary: Python API for accessing BleBox smart home devices
Home-page: https://github.com/blebox/blebox_uniapi
Author: BleBox
Author-email: opensource@blebox.eu
License: Apache Software License 2.0
Keywords: blebox_uniapi
Classifier: Development Status :: 2 - Pre-Alpha
Classifier: Intended Audience :: Developers
Classifier: License :: OSI Approved :: Apache Software License
Classifier: Natural Language :: English
Classifier: Programming Language :: Python :: 3.9
Classifier: Programming Language :: Python :: 3.10
Requires-Python: >=3.9
License-File: LICENSE
Requires-Dist: aiohttp>=3
Requires-Dist: jmespath>1.0.0
